{
  "archived": false,
  "branch": "main",
  "ci_support_linux_64_.yaml": "channel_sources:\n- conda-forge\nchannel_targets:\n- conda-forge main\ndocker_image:\n- quay.io/condaforge/linux-anvil-x86_64:alma9\npython_min:\n- '3.10'\n",
  "conda-forge.yml": {
    "conda_build": {
      "error_overlinking": true
    },
    "conda_build_tool": "rattler-build",
    "conda_forge_output_validation": true,
    "github": {
      "branch_name": "main",
      "tooling_branch_name": "main"
    }
  },
  "feedstock_hash": "00c2ab4dfebe615d272edf852cc898a82d1c2d34",
  "feedstock_hash_ts": 1770133581,
  "feedstock_name": "scippnexus",
  "hash_type": "sha256",
  "linux_64_meta_yaml": {
    "about": {
      "home": "https://scipp.github.io/scippnexus/",
      "license": "BSD-3-Clause",
      "license_family": "BSD-3-Clause",
      "license_file": "LICENSE",
      "summary": "An h5py-like utility for NeXus files with seamless Scipp integration"
    },
    "build": {
      "noarch": "python",
      "number": "0",
      "script": "${{ PYTHON }} -m pip install . -vv --no-deps --no-build-isolation"
    },
    "extra": {
      "recipe-maintainers": [
        "MridulS",
        "conda-forge/scipp"
      ]
    },
    "outputs": [
      {
        "build": null,
        "name": "scippnexus",
        "requirements": {
          "build": [],
          "host": [
            "python 3.11.*",
            "setuptools >=68",
            "setuptools-scm >=8.0",
            "pip"
          ],
          "run": [
            "python >=3.11",
            "python-dateutil",
            "scipp >=24.2.0",
            "scipy >=1.10.0",
            "h5py >=3.12"
          ]
        },
        "tests": [
          {
            "python": {
              "imports": [
                "scippnexus"
              ],
              "python_version": "3.11.*"
            }
          }
        ],
        "version": "26.1.1"
      }
    ],
    "package": {
      "name": "scippnexus",
      "version": "26.1.1"
    },
    "requirements": {
      "host": [
        "python 3.11.*",
        "setuptools >=68",
        "setuptools-scm >=8.0",
        "pip"
      ],
      "run": [
        "python >=3.11",
        "python-dateutil",
        "scipp >=24.2.0",
        "scipy >=1.10.0",
        "h5py >=3.12"
      ]
    },
    "schema_version": 1,
    "source": {
      "sha256": "6c98381110b16b3e6b67e925e46b56369145d748ca60956bc04e5c7664f27601",
      "url": "https://pypi.org/packages/source/s/scippnexus/scippnexus-26.1.1.tar.gz"
    }
  },
  "linux_64_requirements": {
    "build": {
      "__set__": true,
      "elements": []
    },
    "host": {
      "__set__": true,
      "elements": [
        "pip",
        "python",
        "setuptools",
        "setuptools-scm"
      ]
    },
    "run": {
      "__set__": true,
      "elements": [
        "h5py",
        "python",
        "python-dateutil",
        "scipp",
        "scipy"
      ]
    },
    "test": {
      "__set__": true,
      "elements": [
        "pip"
      ]
    }
  },
  "meta_yaml": {
    "about": {
      "home": "https://scipp.github.io/scippnexus/",
      "license": "BSD-3-Clause",
      "license_family": "BSD-3-Clause",
      "license_file": "LICENSE",
      "summary": "An h5py-like utility for NeXus files with seamless Scipp integration"
    },
    "build": {
      "noarch": "python",
      "number": "0",
      "script": "${{ PYTHON }} -m pip install . -vv --no-deps --no-build-isolation"
    },
    "extra": {
      "recipe-maintainers": [
        "MridulS",
        "conda-forge/scipp"
      ]
    },
    "outputs": [
      {
        "build": null,
        "name": "scippnexus",
        "requirements": {
          "build": [],
          "host": [
            "python 3.11.*",
            "setuptools >=68",
            "setuptools-scm >=8.0",
            "pip"
          ],
          "run": [
            "python >=3.11",
            "python-dateutil",
            "scipp >=24.2.0",
            "scipy >=1.10.0",
            "h5py >=3.12"
          ]
        },
        "tests": [
          {
            "python": {
              "imports": [
                "scippnexus"
              ],
              "python_version": "3.11.*"
            }
          }
        ],
        "version": "26.1.1"
      }
    ],
    "package": {
      "name": "scippnexus",
      "version": "26.1.1"
    },
    "requirements": {
      "host": [
        "python 3.11.*",
        "setuptools >=68",
        "setuptools-scm >=8.0",
        "pip"
      ],
      "run": [
        "python >=3.11",
        "python-dateutil",
        "scipp >=24.2.0",
        "scipy >=1.10.0",
        "h5py >=3.12"
      ]
    },
    "schema_version": 1,
    "source": {
      "sha256": "6c98381110b16b3e6b67e925e46b56369145d748ca60956bc04e5c7664f27601",
      "url": "https://pypi.org/packages/source/s/scippnexus/scippnexus-26.1.1.tar.gz"
    }
  },
  "name": "scippnexus",
  "outputs_names": {
    "__set__": true,
    "elements": [
      "scippnexus"
    ]
  },
  "parsing_error": false,
  "platforms": [
    "linux_64"
  ],
  "pr_info": {
    "__lazy_json__": "pr_info/scippnexus.json"
  },
  "raw_meta_yaml": "context:\n  name: scippnexus\n  version: \"26.1.1\"\n  python_min: \"3.11\"\n\npackage:\n  name: ${{ name }}\n  version: ${{ version }}\n\nsource:\n  url: https://pypi.org/packages/source/${{ name[0] }}/${{ name }}/scippnexus-${{ version }}.tar.gz\n  sha256: 6c98381110b16b3e6b67e925e46b56369145d748ca60956bc04e5c7664f27601\n\nbuild:\n  number: 0\n  noarch: python\n  script: ${{ PYTHON }} -m pip install . -vv --no-deps --no-build-isolation\n\nrequirements:\n  host:\n    - python ${{ python_min }}.*\n    - setuptools >=68\n    - setuptools-scm >=8.0\n    - pip\n  run:\n    - python >=${{ python_min }}\n    - python-dateutil\n    - scipp >=24.02.0\n    - scipy >=1.10.0\n    - h5py >=3.12\n\ntests:\n  - python:\n      imports:\n        - scippnexus\n      pip_check: true\n      python_version: ${{ python_min }}.*\n\nabout:\n  homepage: https://scipp.github.io/scippnexus/\n  summary: An h5py-like utility for NeXus files with seamless Scipp integration\n  license: BSD-3-Clause\n  license_file: LICENSE\n\nextra:\n  recipe-maintainers:\n    - MridulS\n    - conda-forge/scipp\n",
  "req": {
    "__set__": true,
    "elements": [
      "h5py",
      "pip",
      "python",
      "python-dateutil",
      "scipp",
      "scipy",
      "setuptools",
      "setuptools-scm"
    ]
  },
  "requirements": {
    "build": {
      "__set__": true,
      "elements": []
    },
    "host": {
      "__set__": true,
      "elements": [
        "pip",
        "python",
        "setuptools",
        "setuptools-scm"
      ]
    },
    "run": {
      "__set__": true,
      "elements": [
        "h5py",
        "python",
        "python-dateutil",
        "scipp",
        "scipy"
      ]
    },
    "test": {
      "__set__": true,
      "elements": [
        "pip"
      ]
    }
  },
  "strong_exports": false,
  "total_requirements": {
    "build": {
      "__set__": true,
      "elements": []
    },
    "host": {
      "__set__": true,
      "elements": [
        "pip",
        "python 3.11.*",
        "setuptools >=68",
        "setuptools-scm >=8.0"
      ]
    },
    "run": {
      "__set__": true,
      "elements": [
        "h5py >=3.12",
        "python >=3.11",
        "python-dateutil",
        "scipp >=24.2.0",
        "scipy >=1.10.0"
      ]
    },
    "test": {
      "__set__": true,
      "elements": [
        "pip"
      ]
    }
  },
  "url": "https://pypi.org/packages/source/s/scippnexus/scippnexus-26.1.1.tar.gz",
  "version": "26.1.1",
  "version_pr_info": {
    "__lazy_json__": "version_pr_info/scippnexus.json"
  }
}