{
 "archived": false,
 "branch": "main",
 "conda-forge.yml": {
  "conda_build": {
   "pkg_format": "2"
  },
  "conda_forge_output_validation": true,
  "github": {
   "branch_name": "main",
   "tooling_branch_name": "main"
  }
 },
 "feedstock_name": "protoc-gen-swagger",
 "hash_type": "sha256",
 "linux_64_meta_yaml": {
  "about": {
   "home": "https://github.com/universe-proton/protoc-gen-swagger",
   "license": "Apache-2.0",
   "license_file": "LICENSE",
   "summary": "A python package for swagger's annotation protobuf files"
  },
  "build": {
   "noarch": "python",
   "number": "0",
   "script": "PYTHON -m pip install . -vv"
  },
  "extra": {
   "recipe-maintainers": [
    "asford"
   ]
  },
  "package": {
   "name": "protoc-gen-swagger",
   "version": "0.1.0"
  },
  "requirements": {
   "host": [
    "pip",
    "python >=3.6"
   ],
   "run": [
    "python >=3.6",
    "protobuf >=3.0.0"
   ]
  },
  "schema_version": 0,
  "source": {
   "sha256": "bf9593eec8e0cac31fef10bd558f2a69babbb2475c67291c1c2ca84763c73067",
   "url": "https://github.com/universe-proton/protoc-gen-swagger/archive/refs/tags/v0.1.0.tar.gz"
  },
  "test": {
   "commands": [
    "pip check"
   ],
   "imports": [
    "protoc_gen_swagger"
   ],
   "requires": [
    "pip"
   ]
  }
 },
 "linux_64_requirements": {
  "build": {
   "__set__": true,
   "elements": []
  },
  "host": {
   "__set__": true,
   "elements": [
    "pip",
    "python"
   ]
  },
  "run": {
   "__set__": true,
   "elements": [
    "protobuf",
    "python"
   ]
  },
  "test": {
   "__set__": true,
   "elements": [
    "pip"
   ]
  }
 },
 "meta_yaml": {
  "about": {
   "home": "https://github.com/universe-proton/protoc-gen-swagger",
   "license": "Apache-2.0",
   "license_file": "LICENSE",
   "summary": "A python package for swagger's annotation protobuf files"
  },
  "build": {
   "noarch": "python",
   "number": "0",
   "script": "PYTHON -m pip install . -vv"
  },
  "extra": {
   "recipe-maintainers": [
    "asford"
   ]
  },
  "package": {
   "name": "protoc-gen-swagger",
   "version": "0.1.0"
  },
  "requirements": {
   "host": [
    "pip",
    "python >=3.6"
   ],
   "run": [
    "python >=3.6",
    "protobuf >=3.0.0"
   ]
  },
  "schema_version": 0,
  "source": {
   "sha256": "bf9593eec8e0cac31fef10bd558f2a69babbb2475c67291c1c2ca84763c73067",
   "url": "https://github.com/universe-proton/protoc-gen-swagger/archive/refs/tags/v0.1.0.tar.gz"
  },
  "test": {
   "commands": [
    "pip check"
   ],
   "imports": [
    "protoc_gen_swagger"
   ],
   "requires": [
    "pip"
   ]
  }
 },
 "name": "protoc-gen-swagger",
 "outputs_names": {
  "__set__": true,
  "elements": [
   "protoc-gen-swagger"
  ]
 },
 "parsing_error": false,
 "platforms": [
  "linux_64"
 ],
 "pr_info": {
  "__lazy_json__": "pr_info/protoc-gen-swagger.json"
 },
 "raw_meta_yaml": "{% set name = \"protoc-gen-swagger\" %}\n{% set version = \"0.1.0\" %}\n\npackage:\n  name: {{ name|lower }}\n  version: {{ version }}\n\nsource:\n  # Only uploaded to pypi as a .whl, not .sdist, so package is specified as github source archive\n  url: https://github.com/universe-proton/protoc-gen-swagger/archive/refs/tags/v{{ version }}.tar.gz\n  sha256: bf9593eec8e0cac31fef10bd558f2a69babbb2475c67291c1c2ca84763c73067\n\nbuild:\n  noarch: python\n  script: {{ PYTHON }} -m pip install . -vv\n  number: 0\n\nrequirements:\n  host:\n    - pip\n    - python >=3.6\n  run:\n    - python >=3.6\n    - protobuf >=3.0.0\n\ntest:\n  imports:\n    - protoc_gen_swagger\n  commands:\n    - pip check\n  requires:\n    - pip\n\nabout:\n  home: https://github.com/universe-proton/protoc-gen-swagger\n  summary: A python package for swagger's annotation protobuf files\n  license: Apache-2.0\n  license_file: LICENSE\n\nextra:\n  recipe-maintainers:\n    - asford\n",
 "req": {
  "__set__": true,
  "elements": [
   "pip",
   "protobuf",
   "python"
  ]
 },
 "requirements": {
  "build": {
   "__set__": true,
   "elements": []
  },
  "host": {
   "__set__": true,
   "elements": [
    "pip",
    "python"
   ]
  },
  "run": {
   "__set__": true,
   "elements": [
    "protobuf",
    "python"
   ]
  },
  "test": {
   "__set__": true,
   "elements": [
    "pip"
   ]
  }
 },
 "strong_exports": false,
 "total_requirements": {
  "build": {
   "__set__": true,
   "elements": []
  },
  "host": {
   "__set__": true,
   "elements": [
    "pip",
    "python >=3.6"
   ]
  },
  "run": {
   "__set__": true,
   "elements": [
    "protobuf >=3.0.0",
    "python >=3.6"
   ]
  },
  "test": {
   "__set__": true,
   "elements": [
    "pip"
   ]
  }
 },
 "url": "https://github.com/universe-proton/protoc-gen-swagger/archive/refs/tags/v0.1.0.tar.gz",
 "version": "0.1.0",
 "version_pr_info": {
  "__lazy_json__": "version_pr_info/protoc-gen-swagger.json"
 }
}