{
  "ETag": "W/\"449e3e3aa54f2fedbed50786674028491ea74f59df83a7d8bd46f15ab7987ec2\"",
  "Last-Modified": "Tue, 18 Nov 2025 20:52:18 GMT",
  "base": {
    "repo": {
      "name": "echopop-feedstock"
    }
  },
  "closed_at": "2025-11-18T20:52:18Z",
  "created_at": "2025-11-13T06:58:18Z",
  "draft": false,
  "e_tag": "\"f67ae27af99263306d6b7a0544c54a1b569d2177fe9e9fc652cf6eb20f0c40aa\"",
  "head": {
    "ref": "this_is_not_a_branch"
  },
  "html_url": "https://github.com/conda-forge/echopop-feedstock/pull/3",
  "id": 3005676674,
  "labels": [],
  "last_modified": null,
  "mergeable": null,
  "mergeable_state": "unknown",
  "merged": true,
  "merged_at": "2025-11-18T20:52:18Z",
  "number": 3,
  "state": "closed",
  "updated_at": "2025-11-18T20:52:18Z"
}