{
  "ETag": "W/\"e43d651c8984e6158088e209dc7324b8d1532336e1c00cb605b63090205830ba\"",
  "Last-Modified": "Tue, 23 Sep 2025 17:07:53 GMT",
  "base": {
    "repo": {
      "name": "r-babynames-feedstock"
    }
  },
  "closed_at": "2025-09-23T17:07:49Z",
  "created_at": "2025-09-23T17:00:12Z",
  "draft": false,
  "e_tag": "\"949a076fa490a1d6627a040d71496bba46ed9e6db2503254f9c9d75436185caa\"",
  "head": {
    "ref": "this_is_not_a_branch"
  },
  "html_url": "https://github.com/conda-forge/r-babynames-feedstock/pull/4",
  "id": 2854003156,
  "labels": [],
  "last_modified": null,
  "mergeable": null,
  "mergeable_state": "unknown",
  "merged": true,
  "merged_at": "2025-09-23T17:07:49Z",
  "number": 4,
  "state": "closed",
  "updated_at": "2025-09-23T17:07:53Z"
}