{
 "ETag": "W/\"0ce843438e9600d20167b800ed99d81b10eb4a849f898cc6578d27190efee6e8\"",
 "Last-Modified": "Mon, 09 Sep 2024 22:27:45 GMT",
 "base": {
  "repo": {
   "name": "nvidia-apex-feedstock"
  }
 },
 "closed_at": null,
 "created_at": "2024-08-24T08:33:51Z",
 "draft": false,
 "head": {
  "ref": "rebuild-pytorch24-0-1_hf13441"
 },
 "html_url": "https://github.com/conda-forge/nvidia-apex-feedstock/pull/50",
 "id": 2035253271,
 "labels": [],
 "mergeable": true,
 "mergeable_state": "clean",
 "merged": false,
 "merged_at": null,
 "number": 50,
 "state": "open",
 "updated_at": "2024-09-09T22:27:45Z"
}