{
  "base": {
    "repo": {
      "name": "apache-airflow-providers-facebook-feedstock"
    }
  },
  "closed_at": null,
  "created_at": "2026-01-18T13:11:06Z",
  "draft": false,
  "e_tag": "\"5cf4d323833f9b8146998da96740e35364f1227ef897024f2bebe4462424278c\"",
  "head": {
    "ref": "3.9.2_ha4599d"
  },
  "html_url": "https://github.com/conda-forge/apache-airflow-providers-facebook-feedstock/pull/30",
  "id": 3185321890,
  "labels": [],
  "last_fetched": "2026-01-18T13:11:07.235142",
  "last_modified": null,
  "mergeable": null,
  "mergeable_state": "unknown",
  "merged": false,
  "merged_at": null,
  "number": 30,
  "state": "open",
  "updated_at": "2026-01-18T13:11:06Z"
}