{
  "ETag": "W/\"c1c3060f8f2a52010f979cbbb86888cc2e741dd28338cdc9e1cfd3f3915dc255\"",
  "Last-Modified": "Fri, 27 Mar 2026 14:42:05 GMT",
  "base": {
    "repo": {
      "name": "superqt-feedstock"
    }
  },
  "closed_at": null,
  "created_at": "2026-03-27T14:40:35Z",
  "draft": false,
  "e_tag": "\"3ddc60d62bcf8e84f9966cfe37bf12ddc5d5ac5a1ba248b7c4a9d93eb895b9cb\"",
  "head": {
    "ref": "0.8.1_h2a9d18"
  },
  "html_url": "https://github.com/conda-forge/superqt-feedstock/pull/46",
  "id": 3457310027,
  "labels": [],
  "last_fetched": "2026-03-27T18:09:10.165312",
  "last_modified": null,
  "mergeable": true,
  "mergeable_state": "clean",
  "merged": false,
  "merged_at": null,
  "number": 46,
  "state": "open",
  "updated_at": "2026-03-27T14:42:05Z"
}