{
  "archived": false,
  "branch": "main",
  "ci_support_linux_64_.yaml": "channel_sources:\n- conda-forge\nchannel_targets:\n- conda-forge main\ndocker_image:\n- quay.io/condaforge/linux-anvil-x86_64:alma9\npython_min:\n- '3.10'\n",
  "conda-forge.yml": {
    "conda_build": {
      "error_overlinking": true
    },
    "conda_forge_output_validation": true,
    "github": {
      "branch_name": "main",
      "tooling_branch_name": "main"
    }
  },
  "feedstock_hash": "7c02a33a869555425ecb047d0531c93cb384abaa",
  "feedstock_hash_ts": 1762355861,
  "feedstock_name": "felupe",
  "hash_type": "sha256",
  "linux_64_meta_yaml": {
    "about": {
      "dev_url": "https://github.com/adtzlr/felupe",
      "home": "https://pypi.org/project/felupe/",
      "license": "GPL-3.0-only",
      "license_file": "LICENSE",
      "summary": "Finite Element Analysis"
    },
    "build": {
      "noarch": "python",
      "number": "0",
      "script": "PYTHON -m pip install . -vv --no-deps --no-build-isolation"
    },
    "extra": {
      "recipe-maintainers": [
        "adtzlr"
      ]
    },
    "package": {
      "name": "felupe",
      "version": "9.5.0"
    },
    "requirements": {
      "host": [
        "python 3.10",
        "setuptools >=61",
        "pip"
      ],
      "run": [
        "python >=3.10",
        "numpy",
        "scipy"
      ]
    },
    "schema_version": 0,
    "source": {
      "sha256": "fa0f5ee235c545024e1f8be5db42a4689fe61a26eeef06a7289d1ae4be2a5283",
      "url": "https://pypi.org/packages/source/f/felupe/felupe-9.5.0.tar.gz"
    },
    "test": {
      "commands": [
        "pip check"
      ],
      "imports": [
        "felupe"
      ],
      "requires": [
        "python 3.10",
        "pip"
      ]
    }
  },
  "linux_64_requirements": {
    "build": {
      "__set__": true,
      "elements": []
    },
    "host": {
      "__set__": true,
      "elements": [
        "pip",
        "python",
        "setuptools"
      ]
    },
    "run": {
      "__set__": true,
      "elements": [
        "numpy",
        "python",
        "scipy"
      ]
    },
    "test": {
      "__set__": true,
      "elements": [
        "pip",
        "python"
      ]
    }
  },
  "meta_yaml": {
    "about": {
      "dev_url": "https://github.com/adtzlr/felupe",
      "home": "https://pypi.org/project/felupe/",
      "license": "GPL-3.0-only",
      "license_file": "LICENSE",
      "summary": "Finite Element Analysis"
    },
    "build": {
      "noarch": "python",
      "number": "0",
      "script": "PYTHON -m pip install . -vv --no-deps --no-build-isolation"
    },
    "extra": {
      "recipe-maintainers": [
        "adtzlr"
      ]
    },
    "package": {
      "name": "felupe",
      "version": "9.5.0"
    },
    "requirements": {
      "host": [
        "python 3.10",
        "setuptools >=61",
        "pip"
      ],
      "run": [
        "python >=3.10",
        "numpy",
        "scipy"
      ]
    },
    "schema_version": 0,
    "source": {
      "sha256": "fa0f5ee235c545024e1f8be5db42a4689fe61a26eeef06a7289d1ae4be2a5283",
      "url": "https://pypi.org/packages/source/f/felupe/felupe-9.5.0.tar.gz"
    },
    "test": {
      "commands": [
        "pip check"
      ],
      "imports": [
        "felupe"
      ],
      "requires": [
        "python 3.10",
        "pip"
      ]
    }
  },
  "name": "felupe",
  "outputs_names": {
    "__set__": true,
    "elements": [
      "felupe"
    ]
  },
  "parsing_error": false,
  "platforms": [
    "linux_64"
  ],
  "pr_info": {
    "__lazy_json__": "pr_info/felupe.json"
  },
  "raw_meta_yaml": "{% set name = \"felupe\" %}\n{% set version = \"9.5.0\" %}\n\npackage:\n  name: {{ name|lower }}\n  version: {{ version }}\n\nsource:\n  url: https://pypi.org/packages/source/{{ name[0] }}/{{ name }}/felupe-{{ version }}.tar.gz\n  sha256: fa0f5ee235c545024e1f8be5db42a4689fe61a26eeef06a7289d1ae4be2a5283\n\nbuild:\n  noarch: python\n  script: {{ PYTHON }} -m pip install . -vv --no-deps --no-build-isolation\n  number: 0\n\nrequirements:\n  host:\n    - python {{ python_min }}\n    - setuptools >=61\n    - pip\n  run:\n    - python >={{ python_min }}\n    - numpy\n    - scipy\n\ntest:\n  imports:\n    - felupe\n  commands:\n    - pip check\n  requires:\n    - python {{ python_min }}\n    - pip\n\nabout:\n  home: https://pypi.org/project/felupe/\n  summary: Finite Element Analysis\n  dev_url: https://github.com/adtzlr/felupe\n  license: GPL-3.0-only\n  license_file: LICENSE\n\nextra:\n  recipe-maintainers:\n    - adtzlr\n",
  "req": {
    "__set__": true,
    "elements": [
      "numpy",
      "pip",
      "python",
      "scipy",
      "setuptools"
    ]
  },
  "requirements": {
    "build": {
      "__set__": true,
      "elements": []
    },
    "host": {
      "__set__": true,
      "elements": [
        "pip",
        "python",
        "setuptools"
      ]
    },
    "run": {
      "__set__": true,
      "elements": [
        "numpy",
        "python",
        "scipy"
      ]
    },
    "test": {
      "__set__": true,
      "elements": [
        "pip",
        "python"
      ]
    }
  },
  "strong_exports": false,
  "total_requirements": {
    "build": {
      "__set__": true,
      "elements": []
    },
    "host": {
      "__set__": true,
      "elements": [
        "pip",
        "python 3.10",
        "setuptools >=61"
      ]
    },
    "run": {
      "__set__": true,
      "elements": [
        "numpy",
        "python >=3.10",
        "scipy"
      ]
    },
    "test": {
      "__set__": true,
      "elements": [
        "pip",
        "python 3.10"
      ]
    }
  },
  "url": "https://pypi.org/packages/source/f/felupe/felupe-9.5.0.tar.gz",
  "version": "9.5.0",
  "version_pr_info": {
    "__lazy_json__": "version_pr_info/felupe.json"
  }
}