{
 "base": {
  "repo": {
   "name": "atomman-feedstock"
  }
 },
 "closed_at": null,
 "created_at": "2025-02-26T22:16:53Z",
 "draft": false,
 "e_tag": "\"c11a093088f25180168b89a72bd2b0634571cdd2be810015cc0ca029b1532aff\"",
 "head": {
  "ref": "rebuild-python313-0-1_hbbbd7e"
 },
 "html_url": "https://github.com/conda-forge/atomman-feedstock/pull/43",
 "id": 2360808347,
 "labels": [],
 "last_modified": null,
 "mergeable": null,
 "mergeable_state": "unknown",
 "merged": false,
 "merged_at": null,
 "number": 43,
 "state": "open",
 "updated_at": "2025-02-26T22:16:53Z"
}