{
 "ETag": "W/\"f4aa13a6764fd0b538081758e7c500a7bee73c533ccfbbd37d06415ff3486ac3\"",
 "Last-Modified": "Fri, 17 Jan 2025 16:24:26 GMT",
 "base": {
  "repo": {
   "name": "easycheck-feedstock"
  }
 },
 "closed_at": null,
 "created_at": "2025-01-17T14:34:50Z",
 "draft": false,
 "e_tag": "\"9b1a15772e3e4c57aa934a86eeda7d202063f926c9b3a7b17167612419ea004d\"",
 "head": {
  "ref": "0.12.1_hbe534b"
 },
 "html_url": "https://github.com/conda-forge/easycheck-feedstock/pull/8",
 "id": 2284455004,
 "labels": [],
 "last_modified": null,
 "mergeable": true,
 "mergeable_state": "clean",
 "merged": false,
 "merged_at": null,
 "number": 8,
 "state": "open",
 "updated_at": "2025-01-17T16:24:26Z"
}