{
 "ETag": "W/\"fea46a47e35ec0dcb6c466c128c54a24ea85bf1478c5b9c6fdd8c81c31ca2fe1\"",
 "Last-Modified": "Wed, 26 Feb 2025 04:00:19 GMT",
 "base": {
  "repo": {
   "name": "boto3-stubs-feedstock"
  }
 },
 "closed_at": "2025-02-26T03:59:41Z",
 "created_at": "2025-02-26T03:54:25Z",
 "draft": false,
 "e_tag": "\"c4ad89206164b6154186515b7b5956f96f4316e14fb32138d072012af2c74dee\"",
 "head": {
  "ref": "this_is_not_a_branch"
 },
 "html_url": "https://github.com/conda-forge/boto3-stubs-feedstock/pull/929",
 "id": 2358239254,
 "labels": [],
 "last_modified": null,
 "mergeable": null,
 "mergeable_state": "unknown",
 "merged": true,
 "merged_at": "2025-02-26T03:59:41Z",
 "number": 929,
 "state": "closed",
 "updated_at": "2025-02-26T04:00:19Z"
}