{
  "ETag": "W/\"1821ac934c7364b248edb527219f96455670d2c0fd9bb2ceba1e21703036bd16\"",
  "Last-Modified": "Wed, 24 Sep 2025 13:44:36 GMT",
  "base": {
    "repo": {
      "name": "r-cnogpro-feedstock"
    }
  },
  "closed_at": "2025-09-24T13:40:20Z",
  "created_at": "2025-09-24T13:34:56Z",
  "draft": false,
  "e_tag": "\"e2ef1086c7b624eef006a835ffa45c75600b3863c2aa6e9385e1bc48c96d3e0c\"",
  "head": {
    "ref": "this_is_not_a_branch"
  },
  "html_url": "https://github.com/conda-forge/r-cnogpro-feedstock/pull/9",
  "id": 2857005794,
  "labels": [],
  "last_modified": null,
  "mergeable": null,
  "mergeable_state": "unknown",
  "merged": true,
  "merged_at": "2025-09-24T13:40:20Z",
  "number": 9,
  "state": "closed",
  "updated_at": "2025-09-24T13:44:36Z"
}