{
  "base": {
    "repo": {
      "name": "rustac-feedstock"
    }
  },
  "closed_at": null,
  "created_at": "2025-10-08T21:10:28Z",
  "draft": false,
  "e_tag": "\"77a1948f07ac0bab9d455dd0ac08c6ecffb4aa9e12231057b1c90d993410f28d\"",
  "head": {
    "ref": "0.8.3_hdb5949"
  },
  "html_url": "https://github.com/conda-forge/rustac-feedstock/pull/11",
  "id": 2898756008,
  "labels": [],
  "last_modified": null,
  "mergeable": null,
  "mergeable_state": "unknown",
  "merged": false,
  "merged_at": null,
  "number": 11,
  "state": "open",
  "updated_at": "2025-10-08T21:10:28Z"
}