{
  "ETag": "W/\"c0b00cef36d7e6225b2faa40ec0a26381b089227c40a62065c2903bcfaa223b2\"",
  "Last-Modified": "Fri, 13 Mar 2026 06:23:55 GMT",
  "base": {
    "repo": {
      "name": "langsmith-feedstock"
    }
  },
  "closed_at": null,
  "created_at": "2026-03-13T06:22:08Z",
  "draft": false,
  "e_tag": "\"842872d80c8b603b61217e8a94fd93c963d70be30a120b7bfafc1fda402e840f\"",
  "head": {
    "ref": "0.7.17_hbba91d"
  },
  "html_url": "https://github.com/conda-forge/langsmith-feedstock/pull/248",
  "id": 3393460233,
  "labels": [],
  "last_fetched": "2026-03-13T08:06:47.200506",
  "last_modified": null,
  "mergeable": true,
  "mergeable_state": "clean",
  "merged": false,
  "merged_at": null,
  "number": 248,
  "state": "open",
  "updated_at": "2026-03-13T06:23:55Z"
}