{
  "ETag": "W/\"3837ae591224d5ee433ba2f844a2a9683c705cf3f6a2803cbd811012b212dab6\"",
  "Last-Modified": "Sat, 31 Jan 2026 19:27:32 GMT",
  "base": {
    "repo": {
      "name": "genomekit-feedstock"
    }
  },
  "closed_at": "2026-01-31T19:27:32Z",
  "created_at": "2026-01-31T02:25:29Z",
  "draft": false,
  "e_tag": "\"4a1c204142fd1ca36b6a84298e2273f0041f31543f365a1fbdf95c1d5cb6de59\"",
  "head": {
    "ref": "this_is_not_a_branch"
  },
  "html_url": "https://github.com/conda-forge/genomekit-feedstock/pull/80",
  "id": 3229884522,
  "labels": [],
  "last_fetched": "2026-01-31T19:28:20.113581",
  "last_modified": null,
  "mergeable": null,
  "mergeable_state": "unknown",
  "merged": true,
  "merged_at": "2026-01-31T19:27:32Z",
  "number": 80,
  "state": "closed",
  "updated_at": "2026-01-31T19:27:32Z"
}