{
  "archived": false,
  "branch": "main",
  "ci_support_linux_64_r_base4.4.yaml": "c_compiler:\n- gcc\nc_compiler_version:\n- '14'\nc_stdlib:\n- sysroot\nc_stdlib_version:\n- '2.17'\nchannel_sources:\n- conda-forge\nchannel_targets:\n- conda-forge main\ncran_mirror:\n- https://cran.r-project.org\ncxx_compiler:\n- gxx\ncxx_compiler_version:\n- '14'\ndocker_image:\n- quay.io/condaforge/linux-anvil-x86_64:alma9\nfortran_compiler:\n- gfortran\nfortran_compiler_version:\n- '14'\npin_run_as_build:\n  r-base:\n    min_pin: x.x\n    max_pin: x.x\nr_base:\n- '4.4'\ntarget_platform:\n- linux-64\nzip_keys:\n- - c_compiler_version\n  - cxx_compiler_version\n  - fortran_compiler_version\n",
  "conda-forge.yml": {
    "bot": {
      "automerge": true
    },
    "conda_build": {
      "pkg_format": "2"
    },
    "conda_forge_output_validation": true,
    "github": {
      "branch_name": "main",
      "tooling_branch_name": "main"
    }
  },
  "feedstock_hash": "d128752ce8d19eab33eba81a467f05903b83fb8c",
  "feedstock_hash_ts": 1766525818,
  "feedstock_name": "r-rpact",
  "hash_type": "sha256",
  "linux_64_meta_yaml": {
    "about": {
      "dev_url": "https://github.com/rpact-com/rpact",
      "doc_url": "https://www.rpact.org/",
      "home": "https://www.rpact.com",
      "license": "LGPL-3.0-only",
      "license_file": [
        "/lib/R/share/licenses/LGPL-3"
      ],
      "summary": "Design and analysis of confirmatory adaptive clinical trials with continuous, binary, and survival endpoints according to the methods described in the monograph by Wassmer and Brannath (2016) <doi:10.1007/978-3-319-32562-0>. This includes classical group sequential as well as multi-stage adaptive hypotheses tests that are based on the combination testing principle."
    },
    "build": {
      "number": "0",
      "rpaths": [
        "lib/R/lib/",
        "lib/"
      ]
    },
    "extra": {
      "recipe-maintainers": [
        "conda-forge/r",
        "thewchan"
      ]
    },
    "package": {
      "name": "r-rpact",
      "version": "4.3.0"
    },
    "requirements": {
      "build": [
        "c_compiler_stub",
        "c_stdlib_stub",
        "cxx_compiler_stub",
        "fortran_compiler_stub",
        "make"
      ],
      "host": [
        "r-base",
        "r-r6 >=2.5.1",
        "r-rcpp >=1.0.3",
        "r-knitr >=1.19",
        "r-rlang"
      ],
      "run": [
        "r-base",
        "r-r6 >=2.5.1",
        "r-rcpp >=1.0.3",
        "r-knitr >=1.19",
        "r-rlang"
      ]
    },
    "schema_version": 0,
    "source": {
      "sha256": "97eb21adeac056296ed7d635589b50163abf2dfca028431896fb858988b78768",
      "url": [
        "https://cran.r-project.org/src/contrib/rpact_4.3.0.tar.gz",
        "https://cran.r-project.org/src/contrib/Archive/rpact/rpact_4.3.0.tar.gz"
      ]
    },
    "test": {
      "commands": [
        "$R -e \"library('rpact')\""
      ]
    }
  },
  "linux_64_requirements": {
    "build": {
      "__set__": true,
      "elements": [
        "c_compiler_stub",
        "c_stdlib_stub",
        "cxx_compiler_stub",
        "fortran_compiler_stub",
        "make"
      ]
    },
    "host": {
      "__set__": true,
      "elements": [
        "r-base",
        "r-knitr",
        "r-r6",
        "r-rcpp",
        "r-rlang"
      ]
    },
    "run": {
      "__set__": true,
      "elements": [
        "r-base",
        "r-knitr",
        "r-r6",
        "r-rcpp",
        "r-rlang"
      ]
    },
    "test": {
      "__set__": true,
      "elements": []
    }
  },
  "meta_yaml": {
    "about": {
      "dev_url": "https://github.com/rpact-com/rpact",
      "doc_url": "https://www.rpact.org/",
      "home": "https://www.rpact.com",
      "license": "LGPL-3.0-only",
      "license_file": [
        "/lib/R/share/licenses/LGPL-3"
      ],
      "summary": "Design and analysis of confirmatory adaptive clinical trials with continuous, binary, and survival endpoints according to the methods described in the monograph by Wassmer and Brannath (2016) <doi:10.1007/978-3-319-32562-0>. This includes classical group sequential as well as multi-stage adaptive hypotheses tests that are based on the combination testing principle."
    },
    "build": {
      "number": "0",
      "rpaths": [
        "lib/R/lib/",
        "lib/"
      ]
    },
    "extra": {
      "recipe-maintainers": [
        "conda-forge/r",
        "thewchan"
      ]
    },
    "package": {
      "name": "r-rpact",
      "version": "4.3.0"
    },
    "requirements": {
      "build": [
        "c_compiler_stub",
        "c_stdlib_stub",
        "cxx_compiler_stub",
        "fortran_compiler_stub",
        "make",
        "m2w64_c_compiler_stub",
        "m2w64_c_stdlib_stub",
        "m2w64_cxx_compiler_stub",
        "m2w64_fortran_compiler_stub",
        "filesystem",
        "sed",
        "coreutils",
        "zip"
      ],
      "host": [
        "r-base",
        "r-r6 >=2.5.1",
        "r-rcpp >=1.0.3",
        "r-knitr >=1.19",
        "r-rlang"
      ],
      "run": [
        "r-base",
        "r-r6 >=2.5.1",
        "r-rcpp >=1.0.3",
        "r-knitr >=1.19",
        "r-rlang"
      ]
    },
    "schema_version": 0,
    "source": {
      "sha256": "97eb21adeac056296ed7d635589b50163abf2dfca028431896fb858988b78768",
      "url": [
        "https://cran.r-project.org/src/contrib/rpact_4.3.0.tar.gz",
        "https://cran.r-project.org/src/contrib/Archive/rpact/rpact_4.3.0.tar.gz"
      ]
    },
    "test": {
      "commands": [
        "$R -e \"library('rpact')\"",
        "\"%R%\" -e \"library('rpact')\""
      ]
    }
  },
  "name": "r-rpact",
  "osx_64_meta_yaml": {
    "about": {
      "dev_url": "https://github.com/rpact-com/rpact",
      "doc_url": "https://www.rpact.org/",
      "home": "https://www.rpact.com",
      "license": "LGPL-3.0-only",
      "license_file": [
        "/lib/R/share/licenses/LGPL-3"
      ],
      "summary": "Design and analysis of confirmatory adaptive clinical trials with continuous, binary, and survival endpoints according to the methods described in the monograph by Wassmer and Brannath (2016) <doi:10.1007/978-3-319-32562-0>. This includes classical group sequential as well as multi-stage adaptive hypotheses tests that are based on the combination testing principle."
    },
    "build": {
      "number": "0",
      "rpaths": [
        "lib/R/lib/",
        "lib/"
      ]
    },
    "extra": {
      "recipe-maintainers": [
        "conda-forge/r",
        "thewchan"
      ]
    },
    "package": {
      "name": "r-rpact",
      "version": "4.3.0"
    },
    "requirements": {
      "build": [
        "c_compiler_stub",
        "c_stdlib_stub",
        "cxx_compiler_stub",
        "fortran_compiler_stub",
        "make"
      ],
      "host": [
        "r-base",
        "r-r6 >=2.5.1",
        "r-rcpp >=1.0.3",
        "r-knitr >=1.19",
        "r-rlang"
      ],
      "run": [
        "r-base",
        "r-r6 >=2.5.1",
        "r-rcpp >=1.0.3",
        "r-knitr >=1.19",
        "r-rlang"
      ]
    },
    "schema_version": 0,
    "source": {
      "sha256": "97eb21adeac056296ed7d635589b50163abf2dfca028431896fb858988b78768",
      "url": [
        "https://cran.r-project.org/src/contrib/rpact_4.3.0.tar.gz",
        "https://cran.r-project.org/src/contrib/Archive/rpact/rpact_4.3.0.tar.gz"
      ]
    },
    "test": {
      "commands": [
        "$R -e \"library('rpact')\""
      ]
    }
  },
  "osx_64_requirements": {
    "build": {
      "__set__": true,
      "elements": [
        "c_compiler_stub",
        "c_stdlib_stub",
        "cxx_compiler_stub",
        "fortran_compiler_stub",
        "make"
      ]
    },
    "host": {
      "__set__": true,
      "elements": [
        "r-base",
        "r-knitr",
        "r-r6",
        "r-rcpp",
        "r-rlang"
      ]
    },
    "run": {
      "__set__": true,
      "elements": [
        "r-base",
        "r-knitr",
        "r-r6",
        "r-rcpp",
        "r-rlang"
      ]
    },
    "test": {
      "__set__": true,
      "elements": []
    }
  },
  "outputs_names": {
    "__set__": true,
    "elements": [
      "r-rpact"
    ]
  },
  "parsing_error": false,
  "platforms": [
    "linux_64",
    "osx_64",
    "win_64"
  ],
  "pr_info": {
    "__lazy_json__": "pr_info/r-rpact.json"
  },
  "raw_meta_yaml": "{% set version = \"4.3.0\" %}\n{% set posix = 'm2-' if win else '' %}\n\npackage:\n  name: r-rpact\n  version: {{ version|replace(\"-\", \"_\") }}\n\nsource:\n  url:\n    - {{ cran_mirror }}/src/contrib/rpact_{{ version }}.tar.gz\n    - {{ cran_mirror }}/src/contrib/Archive/rpact/rpact_{{ version }}.tar.gz\n  sha256: 97eb21adeac056296ed7d635589b50163abf2dfca028431896fb858988b78768\n\nbuild:\n  number: 0\n  rpaths:\n    - lib/R/lib/\n    - lib/\n\nrequirements:\n  build:\n    - {{ compiler('c') }}              # [not win]\n    - {{ stdlib(\"c\") }}                # [not win]\n    - {{ compiler('m2w64_c') }}        # [win]\n    - {{ stdlib(\"m2w64_c\") }}          # [win]\n    - {{ compiler('cxx') }}            # [not win]\n    - {{ compiler('m2w64_cxx') }}      # [win]\n    - {{ compiler('fortran') }}        # [not win]\n    - {{ compiler(\"m2w64_fortran\") }}    # [win]\n    - {{ posix }}filesystem        # [win]\n    - {{ posix }}make\n    - {{ posix }}sed               # [win]\n    - {{ posix }}coreutils         # [win]\n    - {{ posix }}zip               # [win]\n    - cross-r-base {{ r_base }}    # [build_platform != target_platform]\n  host:\n    - r-base\n    - r-r6 >=2.5.1\n    - r-rcpp >=1.0.3\n    - r-knitr >=1.19\n    - r-rlang\n  run:\n    - r-base\n    - r-r6 >=2.5.1\n    - r-rcpp >=1.0.3\n    - r-knitr >=1.19\n    - r-rlang\n\ntest:\n  commands:\n    - $R -e \"library('rpact')\"           # [not win]\n    - \"\\\"%R%\\\" -e \\\"library('rpact')\\\"\"  # [win]\n\nabout:\n  home: https://www.rpact.com\n  dev_url: https://github.com/rpact-com/rpact\n  doc_url: https://www.rpact.org/\n  license: LGPL-3.0-only\n  summary: Design and analysis of confirmatory adaptive clinical trials with continuous, binary, and survival endpoints according to the methods described in the monograph by Wassmer and Brannath (2016) <doi:10.1007/978-3-319-32562-0>. This includes classical group sequential as well as multi-stage adaptive hypotheses tests\n    that are based on the combination testing principle.\n  license_file:\n    - {{ environ[\"PREFIX\"] }}/lib/R/share/licenses/LGPL-3\n\nextra:\n  recipe-maintainers:\n    - conda-forge/r\n    - thewchan\n\n# The original CRAN metadata for this package was:\n# Package: rpact\n# Title: Confirmatory Adaptive Clinical Trial Design and Analysis\n# Version: 3.3.1\n# Date: 2022-08-24\n# Authors@R: c( person( given = \"Gernot\", family = \"Wassmer\", email = \"gernot.wassmer@rpact.com\", role = c(\"aut\")), person( given = \"Friedrich\", family = \"Pahlke\", email = \"friedrich.pahlke@rpact.com\", role = c(\"aut\", \"cre\")) )\n# Description: Design and analysis of confirmatory adaptive clinical trials with continuous, binary, and survival endpoints according to the methods described in the monograph by Wassmer and Brannath (2016) <doi:10.1007/978-3-319-32562-0>. This includes classical group sequential as well as multi-stage adaptive hypotheses tests that are based on the combination testing principle.\n# License: LGPL-3\n# Encoding: UTF-8\n# LazyData: true\n# URL: https://www.rpact.org, https://www.rpact.com, https://github.com/rpact-com/rpact\n# BugReports: https://github.com/rpact-com/rpact/issues\n# Language: en-US\n# Depends: R (>= 3.5.0)\n# Imports: methods, stats, utils, graphics, tools, Rcpp (>= 1.0.0)\n# LinkingTo: Rcpp\n# Suggests: parallel, ggplot2 (>= 2.2.0), testthat (>= 2.0.0), mnormt (>= 1.5-7), knitr (>= 1.19), rmarkdown (>= 1.10)\n# VignetteBuilder: knitr, rmarkdown\n# RoxygenNote: 7.2.1\n# Config/testthat/edition: 3\n# Collate: 'RcppExports.R' 'f_logger.R' 'f_core_constants.R' 'f_core_utilities.R' 'f_core_assertions.R' 'f_analysis_utilities.R' 'f_parameter_set_utilities.R' 'class_core_parameter_set.R' 'class_core_plot_settings.R' 'f_analysis_base.R' 'class_analysis_dataset.R' 'f_core_plot.R' 'class_design.R' 'class_analysis_stage_results.R' 'class_analysis_results.R' 'class_time.R' 'class_design_set.R' 'f_design_utilities.R' 'class_design_plan.R' 'class_design_power_and_asn.R' 'class_event_probabilities.R' 'f_simulation_utilities.R' 'f_simulation_base_survival.R' 'class_simulation_results.R' 'class_summary.R' 'data.R' 'f_analysis_base_means.R' 'f_analysis_base_rates.R' 'f_analysis_base_survival.R' 'f_analysis_enrichment.R' 'f_analysis_enrichment_means.R' 'f_analysis_enrichment_rates.R' 'f_analysis_enrichment_survival.R' 'f_analysis_multiarm.R' 'f_analysis_multiarm_means.R' 'f_analysis_multiarm_rates.R' 'f_analysis_multiarm_survival.R' 'f_core_output_formats.R' 'f_design_fisher_combination_test.R' 'f_design_group_sequential.R' 'f_design_sample_size_calculator.R' 'f_quality_assurance.R' 'f_simulation_base_means.R' 'f_simulation_base_rates.R' 'f_simulation_enrichment.R' 'f_simulation_enrichment_means.R' 'f_simulation_enrichment_rates.R' 'f_simulation_enrichment_survival.R' 'f_simulation_multiarm.R' 'f_simulation_multiarm_means.R' 'f_simulation_multiarm_rates.R' 'f_simulation_multiarm_survival.R' 'parameter_descriptions.R' 'pkgname.R'\n# NeedsCompilation: yes\n# Packaged: 2022-08-24 09:18:23 UTC; fried\n# Author: Gernot Wassmer [aut], Friedrich Pahlke [aut, cre]\n# Maintainer: Friedrich Pahlke <friedrich.pahlke@rpact.com>\n# Repository: CRAN\n# Date/Publication: 2022-08-24 10:50:02 UTC\n# See\n# https://docs.conda.io/projects/conda-build for\n# more information about meta.yaml\n",
  "req": {
    "__set__": true,
    "elements": [
      "c_compiler_stub",
      "c_stdlib_stub",
      "coreutils",
      "cxx_compiler_stub",
      "filesystem",
      "fortran_compiler_stub",
      "m2w64_c_compiler_stub",
      "m2w64_c_stdlib_stub",
      "m2w64_cxx_compiler_stub",
      "m2w64_fortran_compiler_stub",
      "make",
      "r-base",
      "r-knitr",
      "r-r6",
      "r-rcpp",
      "r-rlang",
      "sed",
      "zip"
    ]
  },
  "requirements": {
    "build": {
      "__set__": true,
      "elements": [
        "c_compiler_stub",
        "c_stdlib_stub",
        "coreutils",
        "cxx_compiler_stub",
        "filesystem",
        "fortran_compiler_stub",
        "m2w64_c_compiler_stub",
        "m2w64_c_stdlib_stub",
        "m2w64_cxx_compiler_stub",
        "m2w64_fortran_compiler_stub",
        "make",
        "sed",
        "zip"
      ]
    },
    "host": {
      "__set__": true,
      "elements": [
        "c_compiler_stub",
        "c_stdlib_stub",
        "cxx_compiler_stub",
        "fortran_compiler_stub",
        "r-base",
        "r-knitr",
        "r-r6",
        "r-rcpp",
        "r-rlang"
      ]
    },
    "run": {
      "__set__": true,
      "elements": [
        "c_compiler_stub",
        "c_stdlib_stub",
        "cxx_compiler_stub",
        "fortran_compiler_stub",
        "r-base",
        "r-knitr",
        "r-r6",
        "r-rcpp",
        "r-rlang"
      ]
    },
    "test": {
      "__set__": true,
      "elements": []
    }
  },
  "strong_exports": false,
  "total_requirements": {
    "build": {
      "__set__": true,
      "elements": [
        "c_compiler_stub",
        "c_stdlib_stub",
        "coreutils",
        "cxx_compiler_stub",
        "filesystem",
        "fortran_compiler_stub",
        "m2w64_c_compiler_stub",
        "m2w64_c_stdlib_stub",
        "m2w64_cxx_compiler_stub",
        "m2w64_fortran_compiler_stub",
        "make",
        "sed",
        "zip"
      ]
    },
    "host": {
      "__set__": true,
      "elements": [
        "r-base",
        "r-knitr >=1.19",
        "r-r6 >=2.5.1",
        "r-rcpp >=1.0.3",
        "r-rlang"
      ]
    },
    "run": {
      "__set__": true,
      "elements": [
        "r-base",
        "r-knitr >=1.19",
        "r-r6 >=2.5.1",
        "r-rcpp >=1.0.3",
        "r-rlang"
      ]
    },
    "test": {
      "__set__": true,
      "elements": []
    }
  },
  "url": [
    "https://cran.r-project.org/src/contrib/rpact_4.3.0.tar.gz",
    "https://cran.r-project.org/src/contrib/Archive/rpact/rpact_4.3.0.tar.gz",
    "https://cran.r-project.org/src/contrib/rpact_4.3.0.tar.gz",
    "https://cran.r-project.org/src/contrib/Archive/rpact/rpact_4.3.0.tar.gz",
    "https://cran.r-project.org/src/contrib/rpact_4.3.0.tar.gz",
    "https://cran.r-project.org/src/contrib/Archive/rpact/rpact_4.3.0.tar.gz"
  ],
  "version": "4.3.0",
  "version_pr_info": {
    "__lazy_json__": "version_pr_info/r-rpact.json"
  },
  "win_64_meta_yaml": {
    "about": {
      "dev_url": "https://github.com/rpact-com/rpact",
      "doc_url": "https://www.rpact.org/",
      "home": "https://www.rpact.com",
      "license": "LGPL-3.0-only",
      "license_file": [
        "/lib/R/share/licenses/LGPL-3"
      ],
      "summary": "Design and analysis of confirmatory adaptive clinical trials with continuous, binary, and survival endpoints according to the methods described in the monograph by Wassmer and Brannath (2016) <doi:10.1007/978-3-319-32562-0>. This includes classical group sequential as well as multi-stage adaptive hypotheses tests that are based on the combination testing principle."
    },
    "build": {
      "number": "0",
      "rpaths": [
        "lib/R/lib/",
        "lib/"
      ]
    },
    "extra": {
      "recipe-maintainers": [
        "conda-forge/r",
        "thewchan"
      ]
    },
    "package": {
      "name": "r-rpact",
      "version": "4.3.0"
    },
    "requirements": {
      "build": [
        "m2w64_c_compiler_stub",
        "m2w64_c_stdlib_stub",
        "m2w64_cxx_compiler_stub",
        "m2w64_fortran_compiler_stub",
        "filesystem",
        "make",
        "sed",
        "coreutils",
        "zip"
      ],
      "host": [
        "r-base",
        "r-r6 >=2.5.1",
        "r-rcpp >=1.0.3",
        "r-knitr >=1.19",
        "r-rlang"
      ],
      "run": [
        "r-base",
        "r-r6 >=2.5.1",
        "r-rcpp >=1.0.3",
        "r-knitr >=1.19",
        "r-rlang"
      ]
    },
    "schema_version": 0,
    "source": {
      "sha256": "97eb21adeac056296ed7d635589b50163abf2dfca028431896fb858988b78768",
      "url": [
        "https://cran.r-project.org/src/contrib/rpact_4.3.0.tar.gz",
        "https://cran.r-project.org/src/contrib/Archive/rpact/rpact_4.3.0.tar.gz"
      ]
    },
    "test": {
      "commands": [
        "\"%R%\" -e \"library('rpact')\""
      ]
    }
  },
  "win_64_requirements": {
    "build": {
      "__set__": true,
      "elements": [
        "coreutils",
        "filesystem",
        "m2w64_c_compiler_stub",
        "m2w64_c_stdlib_stub",
        "m2w64_cxx_compiler_stub",
        "m2w64_fortran_compiler_stub",
        "make",
        "sed",
        "zip"
      ]
    },
    "host": {
      "__set__": true,
      "elements": [
        "r-base",
        "r-knitr",
        "r-r6",
        "r-rcpp",
        "r-rlang"
      ]
    },
    "run": {
      "__set__": true,
      "elements": [
        "r-base",
        "r-knitr",
        "r-r6",
        "r-rcpp",
        "r-rlang"
      ]
    },
    "test": {
      "__set__": true,
      "elements": []
    }
  }
}