{
 "ETag": "W/\"82ded780a96b8684c1b77d2df7742f259b4fbcc8668cbb2a0464e5ec0db490ff\"",
 "Last-Modified": "Thu, 24 Oct 2024 02:05:19 GMT",
 "base": {
  "repo": {
   "name": "pdftext-feedstock"
  }
 },
 "closed_at": null,
 "created_at": "2024-10-24T01:59:55Z",
 "draft": false,
 "head": {
  "ref": "0.3.17_hd99965"
 },
 "html_url": "https://github.com/conda-forge/pdftext-feedstock/pull/5",
 "id": 2142442406,
 "labels": [],
 "mergeable": true,
 "mergeable_state": "unstable",
 "merged": false,
 "merged_at": null,
 "number": 5,
 "state": "open",
 "updated_at": "2024-10-24T02:05:19Z"
}