{
 "archived": false,
 "branch": "main",
 "conda-forge.yml": {
  "bot": {
   "automerge": true,
   "inspection": "update-grayskull"
  },
  "conda_build": {
   "pkg_format": "2"
  },
  "conda_forge_output_validation": true,
  "github": {
   "branch_name": "main",
   "tooling_branch_name": "main"
  }
 },
 "feedstock_name": "django-mptt-admin",
 "hash_type": "sha256",
 "last_updated": 1733320991,
 "linux_64_meta_yaml": {
  "about": {
   "description": "Django-mptt-admin provides a nice Django Admin interface for django-mptt models.",
   "dev_url": "https://github.com/mbraak/django-mptt-admin",
   "doc_url": "https://mbraak.github.io/django-mptt-admin/",
   "home": "https://github.com/mbraak/django-mptt-admin",
   "license": "Apache-2.0",
   "license_family": "BSD",
   "license_file": "LICENSE.rst",
   "summary": "Django-mptt-admin provides a nice Django Admin interface for Mptt models"
  },
  "build": {
   "noarch": "python",
   "number": "0",
   "script": "PYTHON -m pip install . -vv"
  },
  "extra": {
   "recipe-maintainers": [
    "cshaley",
    "sannykr",
    "rxm7706"
   ]
  },
  "package": {
   "name": "django-mptt-admin",
   "version": "2.7.0"
  },
  "requirements": {
   "host": [
    "python >=3.8",
    "pip"
   ],
   "run": [
    "python >=3.8",
    "django-mptt"
   ]
  },
  "schema_version": 0,
  "source": {
   "sha256": "3781809f67da86ce07d23f819f78e0682f86b4d850722c6ff2ffae49d83a8e3f",
   "url": "https://pypi.io/packages/source/d/django-mptt-admin/django_mptt_admin-2.7.0.tar.gz"
  },
  "test": {
   "commands": [
    "pip check"
   ],
   "imports": [
    "django_mptt_admin"
   ],
   "requires": [
    "pip"
   ]
  }
 },
 "linux_64_requirements": {
  "build": {
   "__set__": true,
   "elements": []
  },
  "host": {
   "__set__": true,
   "elements": [
    "pip",
    "python"
   ]
  },
  "run": {
   "__set__": true,
   "elements": [
    "django-mptt",
    "python"
   ]
  },
  "test": {
   "__set__": true,
   "elements": [
    "pip"
   ]
  }
 },
 "meta_yaml": {
  "about": {
   "description": "Django-mptt-admin provides a nice Django Admin interface for django-mptt models.",
   "dev_url": "https://github.com/mbraak/django-mptt-admin",
   "doc_url": "https://mbraak.github.io/django-mptt-admin/",
   "home": "https://github.com/mbraak/django-mptt-admin",
   "license": "Apache-2.0",
   "license_family": "BSD",
   "license_file": "LICENSE.rst",
   "summary": "Django-mptt-admin provides a nice Django Admin interface for Mptt models"
  },
  "build": {
   "noarch": "python",
   "number": "0",
   "script": "PYTHON -m pip install . -vv"
  },
  "extra": {
   "recipe-maintainers": [
    "cshaley",
    "sannykr",
    "rxm7706"
   ]
  },
  "package": {
   "name": "django-mptt-admin",
   "version": "2.7.0"
  },
  "requirements": {
   "host": [
    "python >=3.8",
    "pip"
   ],
   "run": [
    "python >=3.8",
    "django-mptt"
   ]
  },
  "schema_version": 0,
  "source": {
   "sha256": "3781809f67da86ce07d23f819f78e0682f86b4d850722c6ff2ffae49d83a8e3f",
   "url": "https://pypi.io/packages/source/d/django-mptt-admin/django_mptt_admin-2.7.0.tar.gz"
  },
  "test": {
   "commands": [
    "pip check"
   ],
   "imports": [
    "django_mptt_admin"
   ],
   "requires": [
    "pip"
   ]
  }
 },
 "name": "django-mptt-admin",
 "outputs_names": {
  "__set__": true,
  "elements": [
   "django-mptt-admin"
  ]
 },
 "parsing_error": false,
 "platforms": [
  "linux_64"
 ],
 "pr_info": {
  "__lazy_json__": "pr_info/django-mptt-admin.json"
 },
 "raw_meta_yaml": "{% set name = \"django-mptt-admin\" %}\n{% set version = \"2.7.0\" %}\n\npackage:\n  name: {{ name|lower }}\n  version: {{ version }}\n\nsource:\n  url: https://pypi.io/packages/source/{{ name[0] }}/{{ name }}/{{ name.replace('-', '_') }}-{{ version }}.tar.gz\n  sha256: 3781809f67da86ce07d23f819f78e0682f86b4d850722c6ff2ffae49d83a8e3f\n\nbuild:\n  noarch: python\n  script: {{ PYTHON }} -m pip install . -vv\n  number: 0\n\nrequirements:\n  host:\n    - python >=3.8\n    - pip\n  run:\n    - python >=3.8\n    - django-mptt\n\ntest:\n  imports:\n    - django_mptt_admin\n  commands:\n    - pip check\n  requires:\n    - pip\n\nabout:\n  home: https://github.com/mbraak/django-mptt-admin\n  license: Apache-2.0\n  license_family: BSD\n  license_file: LICENSE.rst\n  summary: 'Django-mptt-admin provides a nice Django Admin interface for Mptt models'\n  description: Django-mptt-admin provides a nice Django Admin interface for django-mptt models.\n  doc_url: https://mbraak.github.io/django-mptt-admin/\n  dev_url: https://github.com/mbraak/django-mptt-admin\n\nextra:\n  recipe-maintainers:\n    - cshaley\n    - sannykr\n    - rxm7706\n",
 "req": {
  "__set__": true,
  "elements": [
   "django-mptt",
   "pip",
   "python"
  ]
 },
 "requirements": {
  "build": {
   "__set__": true,
   "elements": []
  },
  "host": {
   "__set__": true,
   "elements": [
    "pip",
    "python"
   ]
  },
  "run": {
   "__set__": true,
   "elements": [
    "django-mptt",
    "python"
   ]
  },
  "test": {
   "__set__": true,
   "elements": [
    "pip"
   ]
  }
 },
 "strong_exports": false,
 "total_requirements": {
  "build": {
   "__set__": true,
   "elements": []
  },
  "host": {
   "__set__": true,
   "elements": [
    "pip",
    "python >=3.8"
   ]
  },
  "run": {
   "__set__": true,
   "elements": [
    "django-mptt",
    "python >=3.8"
   ]
  },
  "test": {
   "__set__": true,
   "elements": [
    "pip"
   ]
  }
 },
 "url": "https://pypi.io/packages/source/d/django-mptt-admin/django_mptt_admin-2.7.0.tar.gz",
 "version": "2.7.0",
 "version_pr_info": {
  "__lazy_json__": "version_pr_info/django-mptt-admin.json"
 }
}