{
  "ETag": "W/\"e2cf5388c6b7fcb3e2cca6a3db75bdd7a073efbc9a1769dd2edb5d4cd6a84eff\"",
  "Last-Modified": "Sun, 05 Apr 2026 19:11:23 GMT",
  "base": {
    "repo": {
      "name": "r-meta-feedstock"
    }
  },
  "closed_at": null,
  "created_at": "2026-04-02T12:30:21Z",
  "draft": false,
  "e_tag": "\"2f5b9b2f5c6f277fbd27a95191dc89b219e003ab67dcda275e38e70ab45433ed\"",
  "head": {
    "ref": "8.3_0_h581055"
  },
  "html_url": "https://github.com/conda-forge/r-meta-feedstock/pull/49",
  "id": 3482053020,
  "labels": [],
  "last_fetched": "2026-04-26T20:05:29.155720",
  "last_modified": null,
  "mergeable": true,
  "mergeable_state": "unstable",
  "merged": false,
  "merged_at": null,
  "number": 49,
  "state": "open",
  "updated_at": "2026-04-05T19:11:23Z"
}