{
 "ETag": "W/\"29869ce19c41cb2f308f4c4b22784c4042f4598eba2a0d55621485c7d2f0f41f\"",
 "Last-Modified": "Fri, 13 Sep 2024 01:28:41 GMT",
 "base": {
  "repo": {
   "name": "pyiron_workflow-feedstock"
  }
 },
 "closed_at": null,
 "created_at": "2024-09-13T01:24:10Z",
 "draft": false,
 "head": {
  "ref": "0.10.2_h5a941e"
 },
 "html_url": "https://github.com/conda-forge/pyiron_workflow-feedstock/pull/40",
 "id": 2069852715,
 "labels": [],
 "mergeable": true,
 "mergeable_state": "unstable",
 "merged": false,
 "merged_at": null,
 "number": 40,
 "state": "open",
 "updated_at": "2024-09-13T01:28:41Z"
}