{
 "ETag": "W/\"8e6071a7d73e87a613c61748ac7c3bda8eb1e80b0b2c4c12bcae870b9e36cb6e\"",
 "Last-Modified": "Sun, 12 Jan 2025 11:24:39 GMT",
 "base": {
  "repo": {
   "name": "extensisq-feedstock"
  }
 },
 "closed_at": "2025-01-12T11:24:38Z",
 "created_at": "2025-01-12T09:59:08Z",
 "draft": false,
 "e_tag": "\"ce112b94e3245fca165abaafa1fbfa55d2dce92a0d223b08deada3a3209705bd\"",
 "head": {
  "ref": "this_is_not_a_branch"
 },
 "html_url": "https://github.com/conda-forge/extensisq-feedstock/pull/16",
 "id": 2272454408,
 "labels": [],
 "last_modified": null,
 "mergeable": null,
 "mergeable_state": "unknown",
 "merged": true,
 "merged_at": "2025-01-12T11:24:38Z",
 "number": 16,
 "state": "closed",
 "updated_at": "2025-01-12T11:24:39Z"
}