{
  "ETag": "W/\"51707b6a25bcc03c9b91e2919056a3870a1aae51b22f7fe793b4a1a3ff00cb96\"",
  "Last-Modified": "Mon, 16 Feb 2026 23:40:50 GMT",
  "base": {
    "repo": {
      "name": "evalica-feedstock"
    }
  },
  "closed_at": "2026-02-16T23:40:49Z",
  "created_at": "2026-02-16T05:28:16Z",
  "draft": false,
  "e_tag": "\"326914a1e58813da07b0cf7bfa0dc4f87766b51ac9af713a766b2f8f41e975de\"",
  "head": {
    "ref": "0.4.0.post1_hc40afe"
  },
  "html_url": "https://github.com/conda-forge/evalica-feedstock/pull/15",
  "id": 3288428604,
  "labels": [
    {
      "color": "191970",
      "default": false,
      "description": "Instruct the bot to retry the PR",
      "id": 7231963703,
      "name": "bot-rerun",
      "node_id": "LA_kwDOMZMhcc8AAAABrw8CNw",
      "url": "https://api.github.com/repos/conda-forge/evalica-feedstock/labels/bot-rerun"
    }
  ],
  "last_fetched": "2026-02-16T23:40:51.340666",
  "last_modified": null,
  "mergeable": false,
  "mergeable_state": "dirty",
  "merged": false,
  "merged_at": null,
  "number": 15,
  "state": "closed",
  "updated_at": "2026-02-16T23:40:50Z"
}