{
  "skdh.gait_old": {
    "__set__": true,
    "elements": [
      "scikit-digital-health"
    ]
  },
  "skdh.gait_old.gait": {
    "__set__": true,
    "elements": [
      "scikit-digital-health"
    ]
  },
  "skdh.gait_old.gait_endpoints": {
    "__set__": true,
    "elements": [
      "scikit-digital-health"
    ]
  },
  "skdh.gait_old.gait_endpoints.base": {
    "__set__": true,
    "elements": [
      "scikit-digital-health"
    ]
  },
  "skdh.gait_old.gait_endpoints.gait_endpoints": {
    "__set__": true,
    "elements": [
      "scikit-digital-health"
    ]
  },
  "skdh.gait_old.get_gait_bouts": {
    "__set__": true,
    "elements": [
      "scikit-digital-health"
    ]
  },
  "skdh.gait_old.get_gait_classification": {
    "__set__": true,
    "elements": [
      "scikit-digital-health"
    ]
  },
  "skdh.gait_old.get_gait_events": {
    "__set__": true,
    "elements": [
      "scikit-digital-health"
    ]
  },
  "skdh.gait_old.get_strides": {
    "__set__": true,
    "elements": [
      "scikit-digital-health"
    ]
  },
  "skdh.gait_old.get_turns": {
    "__set__": true,
    "elements": [
      "scikit-digital-health"
    ]
  },
  "skdh.gait_old.model": {
    "__set__": true,
    "elements": [
      "scikit-digital-health"
    ]
  }
}