{
  "base": {
    "repo": {
      "name": "streamlit-folium-feedstock"
    }
  },
  "closed_at": null,
  "created_at": "2026-03-26T21:39:03Z",
  "draft": false,
  "e_tag": "\"5a13616ccc53afdbd4d54622d1b8de7a4527d30fd1e0de250b693691941303cb\"",
  "head": {
    "ref": "0.27.1_h298dbc"
  },
  "html_url": "https://github.com/conda-forge/streamlit-folium-feedstock/pull/65",
  "id": 3453865486,
  "labels": [],
  "last_fetched": "2026-03-26T21:39:04.267961",
  "last_modified": null,
  "mergeable": null,
  "mergeable_state": "unknown",
  "merged": false,
  "merged_at": null,
  "number": 65,
  "state": "open",
  "updated_at": "2026-03-26T21:39:03Z"
}