{
  "pygacode.profiles_gen": {
    "__set__": true,
    "elements": [
      "pygacode"
    ]
  },
  "pygacode.profiles_gen.plot_locpargen_geo": {
    "__set__": true,
    "elements": [
      "pygacode"
    ]
  },
  "pygacode.profiles_gen.plot_profile": {
    "__set__": true,
    "elements": [
      "pygacode"
    ]
  },
  "pygacode.profiles_gen.plot_surf": {
    "__set__": true,
    "elements": [
      "pygacode"
    ]
  },
  "pygacode.profiles_gen.prgen_contour": {
    "__set__": true,
    "elements": [
      "pygacode"
    ]
  },
  "pygacode.profiles_gen.prgen_geqdsk": {
    "__set__": true,
    "elements": [
      "pygacode"
    ]
  },
  "pygacode.profiles_gen.prgen_shape": {
    "__set__": true,
    "elements": [
      "pygacode"
    ]
  },
  "pygacode.profiles_gen.prgen_shape_util": {
    "__set__": true,
    "elements": [
      "pygacode"
    ]
  },
  "pygacode.profiles_gen.prgen_shapeprofile": {
    "__set__": true,
    "elements": [
      "pygacode"
    ]
  }
}